aviary/envs/lfrqa/__init__.py
aviary/envs/lfrqa/env.py
aviary/envs/lfrqa/py.typed
aviary/envs/lfrqa/task.py
aviary/envs/lfrqa/version.py
aviary_lfrqa-0.32.0.dist-info/METADATA
aviary_lfrqa-0.32.0.dist-info/WHEEL
aviary_lfrqa-0.32.0.dist-info/top_level.txt
aviary_lfrqa-0.32.0.dist-info/RECORD
