Metadata-Version: 2.4
Name: aviary.lfrqa
Version: 0.32.0
Summary: LFRQA environment implemented with aviary
Author-email: FutureHouse technical staff <hello@futurehouse.org>
Classifier: Intended Audience :: Developers
Classifier: License :: OSI Approved :: Apache Software License
Classifier: Operating System :: OS Independent
Classifier: Programming Language :: Python :: 3 :: Only
Classifier: Programming Language :: Python :: 3.11
Classifier: Programming Language :: Python :: 3.12
Classifier: Programming Language :: Python :: 3.13
Classifier: Programming Language :: Python :: 3.14
Classifier: Programming Language :: Python
Classifier: Topic :: Scientific/Engineering :: Artificial Intelligence
Requires-Python: >=3.11
Requires-Dist: aviary.labbench
Requires-Dist: fhaviary
Requires-Dist: fhlmi
Requires-Dist: paper-qa>=5.14.0
Requires-Dist: pydantic~=2.0
Provides-Extra: csv
Requires-Dist: pandas; extra == "csv"
Provides-Extra: dev
Requires-Dist: aviary.lfrqa[csv]; extra == "dev"
